fsa_logger/__init__.py
fsa_logger/config/__init__.py
fsa_logger/config/config.py
fsa_logger/config/log_config.py
fsa_logger/fsa_cli/__init__.py
fsa_logger/fsa_cli/cli_common.py
fsa_logger/fsa_cli/cli_sensors.py
fsa_logger/fsa_cli/cli_session.py
fsa_logger/fsa_cli/cli_sessions.py
fsa_logger/fsa_cli/labels.py
fsa_logger/fsa_cli/main_cli.py
fsa_logger/imu_sensor_service.py
fsa_logger/sensor_api.py
fsa_logger/sensor_controller.py
fsa_logger/session_controller.py
fsa_logger/utils.py
fsa_logger-0.1.2.dist-info/entry_points.txt
fsa_logger-0.1.2.dist-info/WHEEL
fsa_logger-0.1.2.dist-info/METADATA
fsa_logger-0.1.2.dist-info/RECORD
