Metadata-Version: 2.1
Name: fsa-logger
Version: 0.1.2
Summary: 
Author: amarco2
Author-email: amarco@unizar.es
Requires-Python: >=3.9,<3.11
Classifier: Programming Language :: Python :: 3
Classifier: Programming Language :: Python :: 3.9
Classifier: Programming Language :: Python :: 3.10
Requires-Dist: blatann (>=0.4.0,<0.5.0)
Requires-Dist: install (>=1.3.5,<2.0.0)
Requires-Dist: openpyxl (>=3.1.2,<4.0.0)
Requires-Dist: pandas (>=2.0.1,<3.0.0)
Requires-Dist: plotly (>=5.13.0,<6.0.0)
Requires-Dist: pyarrow (>=12.0.0,<13.0.0)
Requires-Dist: pydantic[dotenv] (>=1.10.7,<2.0.0)
Requires-Dist: pyfiglet (>=0.8.post1,<0.9)
Requires-Dist: pyserial (>=3.5,<4.0)
Requires-Dist: questionary (>=1.10.0,<2.0.0)
Requires-Dist: scipy (>=1.10.1,<2.0.0)
Requires-Dist: simplepyble (>=0.6.1,<0.7.0)
Requires-Dist: typer[all] (>=0.9.0,<0.10.0)
Requires-Dist: uvicorn (>=0.22.0,<0.23.0)
